setup.py
bin/fess_up
fess_up/__init__.py
fess_up/domainscan.py
fess_up.egg-info/PKG-INFO
fess_up.egg-info/SOURCES.txt
fess_up.egg-info/dependency_links.txt
fess_up.egg-info/requires.txt
fess_up.egg-info/top_level.txt
fess_up/dnsnames/__init__.py