Metadata-Version: 1.1
Name: fess-up
Version: 1.1.3
Summary: DNS record scraper
Home-page: http://github.com/nosmo/fess_up
Author: Hugh Nowlan
Author-email: nosmo@nosmo.me
License: Hacktivismo Enhanced-Source Software License Agreement
Keywords: dns zone scraper
Platform: UNKNOWN
Classifier: Development Status :: 5 - Production/Stable
Classifier: Intended Audience :: Developers
Classifier: Intended Audience :: System Administrators
Classifier: Topic :: Internet :: Name Service (DNS)
Classifier: Topic :: Utilities
